open_sustain_tech/.gitignore
open_sustain_tech/README.md
open_sustain_tech/__init__.py
open_sustain_tech/__main__.py
open_sustain_tech/application_plugin.py
open_sustain_tech/awesomecure/awesome2py.py
open_sustain_tech/awesomecure/md2dict.py
open_sustain_tech/config.py
open_sustain_tech/csv/github_organizations.csv
open_sustain_tech/csv/github_organizations_back.csv
open_sustain_tech/csv/project_analysis.csv
open_sustain_tech/csv/projects.csv
open_sustain_tech/csv/projects_with_readme.csv
open_sustain_tech/docs/AwesomeCure.excalidraw
open_sustain_tech/docs/AwesomeCure.png
open_sustain_tech/docs/AwesomeCure.svg
open_sustain_tech/docs/OST_Analysis.excalidraw
open_sustain_tech/docs/OST_Analysis.png
open_sustain_tech/docs/OST_Analysis.svg
open_sustain_tech/docs/Score_example_plot.png
open_sustain_tech/docs/organizations.png
open_sustain_tech/docs/organizations_forms.png
open_sustain_tech/docs/programming_languages.png
open_sustain_tech/docs/topic_processing.drawio.svg
open_sustain_tech/many_configs.yaml
open_sustain_tech/requirements.txt
open_sustain_tech-1.3.0.dist-info/LICENSE
open_sustain_tech-1.3.0.dist-info/METADATA
open_sustain_tech-1.3.0.dist-info/WHEEL
open_sustain_tech-1.3.0.dist-info/entry_points.txt
open_sustain_tech-1.3.0.dist-info/RECORD
