Metadata-Version: 2.1
Name: open-sustain-tech
Version: 1.3.0
Summary: Awesome List Curated with a Poetry Plugin Support to the Open Sustain Tech CLI Option
Home-page: https://opensustain.tech/
License: MIT
Keywords: awesome-list,poetry,plugin,python,version,sustainability,technology,open,source,software
Author: Abderrahim Guennoune
Author-email: aguennoune@outlook.com
Requires-Python: >=3.8,<3.12
Classifier: Development Status :: 4 - Beta
Classifier: License :: OSI Approved :: MIT License
Classifier: Programming Language :: Python :: 3
Classifier: Programming Language :: Python :: 3.8
Classifier: Programming Language :: Python :: 3.9
Classifier: Programming Language :: Python :: 3.10
Classifier: Programming Language :: Python :: 3.11
Provides-Extra: plugin
Requires-Dist: bs4 (>=0.0.1,<0.0.2)
Requires-Dist: cleo (>=2.1.0,<3.0.0)
Requires-Dist: click (>=8.1.7,<9.0.0)
Requires-Dist: dateparser (>=1.1.8,<2.0.0)
Requires-Dist: handcalcs (>=1.6.5,<2.0.0)
Requires-Dist: importlib-metadata (>=6.8.0,<7.0.0)
Requires-Dist: kaleido (==0.2.1)
Requires-Dist: markdown (>=3.5,<4.0)
Requires-Dist: numpy (>=1.24)
Requires-Dist: pandas (>=1.3.0,<2.0.0)
Requires-Dist: plotly (>=5.18.0,<6.0.0)
Requires-Dist: poetry (>=1.7.0,<2.0.0) ; extra == "plugin"
Requires-Dist: poetry-core (>=1.8.1,<2.0.0)
Requires-Dist: pycaret (>=3.0.0,<4.0.0)
Requires-Dist: pycountry (>=22.3.5,<23.0.0)
Requires-Dist: pygithub (>=2.1.1,<3.0.0)
Requires-Dist: python-dotenv (>=1.0.0,<2.0.0)
Requires-Dist: pyyaml (>=6.0.1,<7.0.0)
Requires-Dist: requests (>=2.31.0,<3.0.0)
Requires-Dist: rich (>=13.6.0,<14.0.0)
Requires-Dist: simple-parsing (>=0.1.4,<0.2.0)
Requires-Dist: termcolor (>=2.3.0,<3.0.0)
Requires-Dist: typer (>=0.9.0,<0.10.0)
Requires-Dist: typer-common-functions (>=0.0.7,<0.0.8)
Project-URL: Bug Tracker, https://github.com/protontypes/AwesomeCure/issues
Project-URL: Repository, https://github.com/aguennoune/AwesomeCure/tree/main
